odoo/addons/stock_picking_report_valued_copy_unvalued/README.rst
odoo/addons/stock_picking_report_valued_copy_unvalued/__init__.py
odoo/addons/stock_picking_report_valued_copy_unvalued/__manifest__.py
odoo/addons/stock_picking_report_valued_copy_unvalued/i18n/es.po
odoo/addons/stock_picking_report_valued_copy_unvalued/models/__init__.py
odoo/addons/stock_picking_report_valued_copy_unvalued/models/res_partner.py
odoo/addons/stock_picking_report_valued_copy_unvalued/models/stock_picking.py
odoo/addons/stock_picking_report_valued_copy_unvalued/readme/CONFIGURE.md
odoo/addons/stock_picking_report_valued_copy_unvalued/readme/CONTRIBUTORS.md
odoo/addons/stock_picking_report_valued_copy_unvalued/readme/DESCRIPTION.md
odoo/addons/stock_picking_report_valued_copy_unvalued/readme/USAGE.md
odoo/addons/stock_picking_report_valued_copy_unvalued/report/stock_picking_report.xml
odoo/addons/stock_picking_report_valued_copy_unvalued/static/description/icon.png
odoo/addons/stock_picking_report_valued_copy_unvalued/static/description/index.html
odoo/addons/stock_picking_report_valued_copy_unvalued/tests/__init__.py
odoo/addons/stock_picking_report_valued_copy_unvalued/tests/test_stock_picking_report_valued_copy_unvalued.py
odoo/addons/stock_picking_report_valued_copy_unvalued/views/res_partner_views.xml
odoo/addons/stock_picking_report_valued_copy_unvalued/views/stock_picking_views.xml
odoo_addon_stock_picking_report_valued_copy_unvalued-17.0.1.0.0.dist-info/METADATA
odoo_addon_stock_picking_report_valued_copy_unvalued-17.0.1.0.0.dist-info/WHEEL
odoo_addon_stock_picking_report_valued_copy_unvalued-17.0.1.0.0.dist-info/top_level.txt
odoo_addon_stock_picking_report_valued_copy_unvalued-17.0.1.0.0.dist-info/RECORD
