Metadata-Version: 2.1
Name: odoo-addon-stock_picking_report_valued_copy_unvalued
Version: 17.0.1.0.0
Requires-Python: >=3.10
Requires-Dist: odoo-addon-stock_picking_report_valued>=17.0dev,<17.1dev
Requires-Dist: odoo>=17.0a,<17.1dev
Summary: Print valued and unvalued delivery slip at the same time
Home-page: https://github.com/sygel-technology/sy-stock-logistics-reporting
License: AGPL-3
Author: =?utf-8?q?Alberto_Mart=C3=ADnez=2C_Odoo_Community_Association_=28OCA=29?=
Author-email: support@odoo-community.org
Classifier: Programming Language :: Python
Classifier: Framework :: Odoo
Classifier: Framework :: Odoo :: 17.0
Classifier: License :: OSI Approved :: GNU Affero General Public License v3
